mcpport/__init__.py
mcpport/client.py
mcpport/gateway.py
mcpport/run.py
mcpport/types.py
mcpport/utils.py
mcpport-0.1.4.dist-info/METADATA
mcpport-0.1.4.dist-info/WHEEL
mcpport-0.1.4.dist-info/entry_points.txt
mcpport-0.1.4.dist-info/licenses/LICENSE
mcpport-0.1.4.dist-info/RECORD
