Metadata-Version: 2.4
Name: mcpport
Version: 0.1.4
Summary: mcpport — A lightweight gateway & registry for Model Context Protocol (MCP), enabling standardized connectivity for AI applications.
Project-URL: Homepage, https://github.com/fangyinc/mcpport
Project-URL: Documentation, https://github.com/fangyinc/mcpport
Project-URL: Repository, https://github.com/fangyinc/mcpport.git
Project-URL: Issues, https://github.com/fangyinc/mcpport/issues
Author-email: fangyinc <staneyffer@gmail.com>
License-Expression: MIT
License-File: LICENSE
Requires-Python: >=3.10
Requires-Dist: flask-cors>=5.0.1
Requires-Dist: flask>=3.1.0
Requires-Dist: httpx<0.28
Requires-Dist: mcp>=1.1.3
Requires-Dist: pydantic>=2.0.0
Requires-Dist: readabilipy>=0.2.0
Requires-Dist: requests>=2.32.3
Requires-Dist: websockets>=15.0.1
Requires-Dist: werkzeug>=3.1.3
